README.md
setup.cfg
setup.py
pomodoro/__init__.py
pomodoro/admin.py
pomodoro/apps.py
pomodoro/forms.py
pomodoro/grafana.py
pomodoro/mixins.py
pomodoro/models.py
pomodoro/permissions.py
pomodoro/renderers.py
pomodoro/rest.py
pomodoro/serializers.py
pomodoro/signals.py
pomodoro/tasks.py
pomodoro/urls.py
pomodoro/util.py
pomodoro/views.py
pomodoro/migrations/0001_squashed_0005_favorite_icon.py
pomodoro/migrations/0002_auto_20170109_0906.py
pomodoro/migrations/0003_notification.py
pomodoro/migrations/0004_favorite_count.py
pomodoro/migrations/0005_auto_20171212_1133.py
pomodoro/migrations/0006_memo.py
pomodoro/migrations/0007_shares.py
pomodoro/migrations/0008_project.py
pomodoro/migrations/0009_project_active.py
pomodoro/migrations/0010_project_duration.py
pomodoro/migrations/__init__.py
pomodoro/notifications/__init__.py
pomodoro/notifications/line.py
pomodoro/notifications/mqtt.py
pomodoro/notifications/prowl.py
pomodoro/standalone/__init__.py
pomodoro/standalone/celery.py
pomodoro/standalone/manage.py
pomodoro/standalone/settings.py
pomodoro/standalone/urls.py
pomodoro/standalone/wsgi.py
pomodoro/templatetags/__init__.py
pomodoro/templatetags/pomodoro.py
pomodoro/tests/__init__.py
pomodoro/tests/test_api.py
pomodoro/tests/test_grafana.py
timeboxed.egg-info/PKG-INFO
timeboxed.egg-info/SOURCES.txt
timeboxed.egg-info/dependency_links.txt
timeboxed.egg-info/entry_points.txt
timeboxed.egg-info/requires.txt
timeboxed.egg-info/top_level.txt